README.md
setup.py
dutools/RSA.py
dutools/__init__.py
dutools/base_settings.py
dutools/constant.py
dutools/crud.py
dutools/exceptions.py
dutools/html.py
dutools/pg_sql.py
dutools/pyneo4j.py
dutools/time.py
dutools/translator.py
dutools.egg-info/PKG-INFO
dutools.egg-info/SOURCES.txt
dutools.egg-info/dependency_links.txt
dutools.egg-info/requires.txt
dutools.egg-info/top_level.txt