Metadata-Version: 2.1
Name: dutools
Version: 0.0.19
Summary: chau‘s  tools
Author: DYZ
Author-email: duyuchau@gmail.com
Maintainer: DYZ
Maintainer-email: duyuchau@gmail.com
License: MIT
Platform: all
Provides-Extra: all
Provides-Extra: mysql
Provides-Extra: pgsql
Provides-Extra: es
Provides-Extra: neo4j
